{
  "forge_marker": 1,
  "defaults": {
    "model": "leaves",
    "textures": {
      "all": "tfc:blocks/material_set/wood/leaves/orange"
    }
  },
  "variants": {
    "normal": [{}],
    "inventory": {
      "model": "leaves",
      "transform": "forge:default-block"
    },
    "state": {
      "normal": {
        "model": "leaves"
      },
      "flowering": {
        "model": "leaves",
        "textures": {
          "all": "tfc:blocks/material_set/wood/leaves/orange",
          "texture": "tfc:blocks/material_set/wood/flowers/orange"
        },
        "submodel": "tfc:fruit_trees/leaves_overlay"
      },
      "fruit": {
        "model": "leaves",
        "textures": {
          "all": "tfc:blocks/material_set/wood/leaves/orange",
          "texture": "tfc:blocks/material_set/wood/fruit/orange"
        },
        "submodel": "tfc:fruit_trees/leaves_overlay"
      }
    }
  }
}
